glibs_test-1.0.0-py2.7-nspkg.pth
glibs/test/__init__.py
glibs/test/_mixins.py
glibs/test/mongo.py
glibs_test-1.0.0.dist-info/METADATA
glibs_test-1.0.0.dist-info/WHEEL
glibs_test-1.0.0.dist-info/namespace_packages.txt
glibs_test-1.0.0.dist-info/top_level.txt
glibs_test-1.0.0.dist-info/RECORD
